contextchain/__init__.py
contextchain/acba.py
contextchain/context_engineer.py
contextchain/core.py
contextchain/dag.py
contextchain/llm.py
contextchain/storage.py
contextchain/vector.py
contextchain/examples/__init__.py
contextchain/examples/fastapi_integration.py
contextchain/examples/sales_query_test.py
contextchain/tests/__init__.py
contextchain/tests/test_acba.py
contextchain/tests/test_context_engineer.py
contextchain/tests/test_core.py
contextchain/tests/test_dag.py
contextchain/tests/test_llm.py
contextchain/tests/test_storage.py
contextchain/tests/test_vector.py
contextchain-1.4.44.dist-info/licenses/LICENSE
contextchain-1.4.44.dist-info/METADATA
contextchain-1.4.44.dist-info/WHEEL
contextchain-1.4.44.dist-info/entry_points.txt
contextchain-1.4.44.dist-info/top_level.txt
contextchain-1.4.44.dist-info/RECORD
