Metadata-Version: 2.4
Name: contextchain
Version: 1.4.44
Summary: ContextChain v2.0: Adaptive context optimization framework for LLMs with MongoDB, vector DB, and multi-backend LLM integration
Author-email: Nihal Nazeer <Nhaal160@gmail.com>
License-Expression: MIT
Project-URL: Homepage, https://github.com/nihalnazeer/contextchain
Project-URL: Bug_Tracker, https://github.com/nihalnazeer/contextchain/issues
Project-URL: Documentation, https://github.com/nihalnazeer/contextchain/blob/main/docs
Classifier: Development Status :: 4 - Beta
Classifier: Intended Audience :: Developers
Classifier: Programming Language :: Python :: 3
Classifier: Programming Language :: Python :: 3.8
Classifier: Programming Language :: Python :: 3.9
Classifier: Programming Language :: Python :: 3.10
Classifier: Programming Language :: Python :: 3.11
Classifier: Operating System :: OS Independent
Requires-Python: >=3.8
License-File: LICENSE
Requires-Dist: pymongo>=4.13.2
Requires-Dist: motor>=3.1.1
Requires-Dist: requests>=2.32.4
Requires-Dist: pydantic>=2.11.7
Requires-Dist: urllib3<2
Requires-Dist: python-dotenv>=1.0.0
Requires-Dist: numpy>=1.26.0
Requires-Dist: torch>=2.0.0
Requires-Dist: sentence-transformers>=2.2.2
Requires-Dist: scikit-learn>=1.3.0
Requires-Dist: faiss-cpu>=1.7.4
Requires-Dist: chromadb>=0.4.0
Requires-Dist: networkx>=3.1
Requires-Dist: jinja2>=3.1.2
Requires-Dist: fastapi>=0.104.0
Requires-Dist: uvicorn>=0.24.0
Requires-Dist: openai>=1.0.0
Requires-Dist: anthropic>=0.7.0
Requires-Dist: ollama>=0.1.0
Requires-Dist: transformers>=4.35.0
Requires-Dist: httpx>=0.24.0
Requires-Dist: pytest>=7.0.0
Requires-Dist: pytest-asyncio>=0.21.0
Dynamic: license-file
